examples/README.md
examples/__init__.py
examples/deploy_full_setup.py
examples/docker-compose.example.yml
examples/ec2-setup.sh
examples/github-actions-ec2.yml
examples/github-actions-full-setup.yml
examples/production-deploy.sh
examples/rollback.sh
examples/setup.sh
examples/ssh_key_management.py
examples/version_check.sh
examples/cloud/README.md
examples/cloud/__init__.py
examples/cloud/ssh_identity_file.py
examples/cloud/ssh_password.py
examples/cloud/template_cloud_setup.py
examples/local/.keep
examples/local/README.md
examples/local/__init__.py
examples/local/template_local_setup.py
vm_tool/__init__.py
vm_tool/alerting.py
vm_tool/audit.py
vm_tool/backup.py
vm_tool/benchmarking.py
vm_tool/cli.py
vm_tool/cloud.py
vm_tool/completion.py
vm_tool/compliance.py
vm_tool/config.py
vm_tool/drift.py
vm_tool/generator.py
vm_tool/health.py
vm_tool/history.py
vm_tool/kubernetes.py
vm_tool/metrics.py
vm_tool/notifications.py
vm_tool/plugins.py
vm_tool/policy.py
vm_tool/rbac.py
vm_tool/recovery.py
vm_tool/reporting.py
vm_tool/runner.py
vm_tool/secrets.py
vm_tool/ssh.py
vm_tool/state.py
vm_tool/validation.py
vm_tool/webhooks.py
vm_tool/strategies/__init__.py
vm_tool/strategies/ab_testing.py
vm_tool/strategies/blue_green.py
vm_tool/strategies/canary.py
vm_tool/vm_setup/cleanup.yml
vm_tool/vm_setup/inventory.yml
vm_tool/vm_setup/k8s.yml
vm_tool/vm_setup/main.yml
vm_tool/vm_setup/monitoring.yml
vm_tool/vm_setup/project_service.yml
vm_tool/vm_setup/push_code.yml
vm_tool/vm_setup/push_code_tasks.yml
vm_tool/vm_setup/setup.yml
vm_tool/vm_setup/setup_project_env.yml
vm_tool/vm_setup/docker/create_docker_service.yml
vm_tool/vm_setup/docker/docker_setup.yml
vm_tool/vm_setup/docker/install_docker_and_compose.yml
vm_tool/vm_setup/docker/login_to_docker_hub.yml
vm_tool/vm_setup/github/git_configuration.yml
vm_tool-1.0.42.dist-info/licenses/LICENSE
vm_tool-1.0.42.dist-info/METADATA
vm_tool-1.0.42.dist-info/WHEEL
vm_tool-1.0.42.dist-info/entry_points.txt
vm_tool-1.0.42.dist-info/top_level.txt
vm_tool-1.0.42.dist-info/RECORD
