Metadata-Version: 2.4
Name: vm_tool
Version: 1.0.42
Summary: A Comprehensive Tool for Setting Up Virtual Machines.
Home-page: https://github.com/thesunnysinha/vm_tool
Author: Sunny Sinha
Author-email: Sunny Sinha <thesunnysinha@gmail.com>
License: MIT
Project-URL: Documentation, https://vm-tool.sunnysinha.online/
Project-URL: Source, https://github.com/thesunnysinha/vm_tool
Project-URL: Tracker, https://github.com/thesunnysinha/vm_tool/issues
Classifier: Development Status :: 5 - Production/Stable
Classifier: Intended Audience :: Developers
Classifier: Intended Audience :: System Administrators
Classifier: License :: OSI Approved :: MIT License
Classifier: Programming Language :: Python
Classifier: Programming Language :: Python :: 3.10
Classifier: Programming Language :: Python :: 3.11
Classifier: Programming Language :: Python :: 3.12
Classifier: Programming Language :: Python :: 3.13
Classifier: Topic :: Software Development :: Build Tools
Classifier: Topic :: System :: Systems Administration
Requires-Python: >=3.9
License-File: LICENSE
Requires-Dist: ansible
Requires-Dist: ansible-runner
Requires-Dist: paramiko
Requires-Dist: pydantic
Requires-Dist: pyyaml
Provides-Extra: dev
Requires-Dist: pytest>=6.0.0; extra == "dev"
Requires-Dist: check-manifest; extra == "dev"
Requires-Dist: twine; extra == "dev"
Requires-Dist: wheel; extra == "dev"
Requires-Dist: bump-my-version; extra == "dev"
Requires-Dist: bandit; extra == "dev"
Requires-Dist: pre-commit; extra == "dev"
Requires-Dist: mkdocs-material; extra == "dev"
Requires-Dist: mkdocstrings[python]; extra == "dev"
Requires-Dist: black; extra == "dev"
Requires-Dist: isort; extra == "dev"
Dynamic: author
Dynamic: home-page
Dynamic: license-file
Dynamic: requires-python
